LICENSE
MANIFEST.in
README.md
requirements.txt
setup.cfg
setup.py
django_mp_markups.egg-info/PKG-INFO
django_mp_markups.egg-info/SOURCES.txt
django_mp_markups.egg-info/dependency_links.txt
django_mp_markups.egg-info/top_level.txt
markups/__init__.py
markups/admin.py
markups/models.py
markups/locale/ru/LC_MESSAGES/django.mo
markups/locale/ru/LC_MESSAGES/django.po
markups/locale/uk/LC_MESSAGES/django.mo
markups/locale/uk/LC_MESSAGES/django.po
markups/migrations/0001_initial.py
markups/migrations/__init__.py