Metadata-Version: 1.1
Name: django-mp-markups
Version: 0.1
Summary: Django markups app
Home-page: https://github.com/pmaigutyak/mp-markups
Author: Paul Maigutyak
Author-email: pmaigutyak@gmail.com
License: MIT
Download-URL: https://github.com/pmaigutyak/mp-markups/archive/0.1.tar.gz
Platform: UNKNOWN
